<odoo>
    <record id="view_order_form_inherit_proposal" model="ir.ui.view">
        <field name="name">view.order.form.inherit.proposal</field>
        <field name="model">sale.order</field>
        <field name="type">form</field>
        <field name="inherit_id" ref="sale.view_order_form"/>
        <field name="arch" type="xml">     
            <field name="partner_shipping_id" position="after">
                <field name="is_proposal" invisible="1"/>
                <field name="billing_email" attrs="{'readonly':[('state','=','sale')],'invisible':[('is_proposal', '=', False)]}"/>
                <field name="billing_phone"  attrs="{'readonly':[('state','=','sale')],'invisible':[('is_proposal', '=', False)]}"/>
                <field name="recurring_id"  attrs="{'readonly':[('state','=','sale')],'invisible':[('is_proposal', '=', False)]}"/>
                
            </field>
            <field name="payment_term_id" position="after">
                <field name="contact_person_id" options="{'no_create_edit': True}" attrs="{'readonly':[('state','=','sale')],'invisible':[('is_proposal', '=', False)]}"/>
                <field name="contact_email"  attrs="{'readonly':[('state','=','sale')],'invisible':[('is_proposal', '=', False)]}"/>
                <field name="contact_phone"  attrs="{'readonly':[('state','=','sale')],'invisible':[('is_proposal', '=', False)]}"/>
                <field name="start_date"  attrs="{'readonly':[('state','=','sale')],'invisible':[('is_proposal', '=', False)]}"/>
                <field name="end_date" attrs="{'readonly':[('state','=','sale')],'invisible':[('is_proposal', '=', False)]}"/>
            </field>
            <field name="note" position="before">
                <group colspan="4">
                     <field name="conditions_id"  attrs="{'readonly':[('state','=','sale')],'invisible':[('is_proposal', '=', False)]}"/>
                </group>
               
            </field>
        
        </field>
    </record>
</odoo>
